blip_sdk/__init__.py
blip_sdk/application.py
blip_sdk/client.py
blip_sdk/client_builder.py
blip_sdk/receiver.py
blip_sdk/extensions/__init__.py
blip_sdk/extensions/extension_base.py
blip_sdk/extensions/analytics/__init__.py
blip_sdk/extensions/analytics/analytics_extension.py
blip_sdk/extensions/analytics/content_type.py
blip_sdk/extensions/analytics/uri_templates.py
blip_sdk/extensions/artificial_intelligence/__init__.py
blip_sdk/extensions/artificial_intelligence/ai_extension.py
blip_sdk/extensions/artificial_intelligence/ai_analytics/__init__.py
blip_sdk/extensions/artificial_intelligence/ai_analytics/ai_analytics_extension.py
blip_sdk/extensions/artificial_intelligence/ai_analytics/content_type.py
blip_sdk/extensions/artificial_intelligence/ai_analytics/uri_templates.py
blip_sdk/extensions/artificial_intelligence/ai_model/__init__.py
blip_sdk/extensions/artificial_intelligence/ai_model/ai_model_extension.py
blip_sdk/extensions/artificial_intelligence/ai_model/content_type.py
blip_sdk/extensions/artificial_intelligence/ai_model/uri_templates.py
blip_sdk/extensions/artificial_intelligence/content_assistant/__init__.py
blip_sdk/extensions/artificial_intelligence/content_assistant/content_assistant_extension.py
blip_sdk/extensions/artificial_intelligence/content_assistant/content_type.py
blip_sdk/extensions/artificial_intelligence/content_assistant/uri_templates.py
blip_sdk/extensions/artificial_intelligence/entities/__init__.py
blip_sdk/extensions/artificial_intelligence/entities/content_type.py
blip_sdk/extensions/artificial_intelligence/entities/entities_extension.py
blip_sdk/extensions/artificial_intelligence/entities/uri_templates.py
blip_sdk/extensions/artificial_intelligence/intents/__init__.py
blip_sdk/extensions/artificial_intelligence/intents/content_type.py
blip_sdk/extensions/artificial_intelligence/intents/intents_extension.py
blip_sdk/extensions/artificial_intelligence/intents/uri_templates.py
blip_sdk-1.0.4.dist-info/LICENSE
blip_sdk-1.0.4.dist-info/METADATA
blip_sdk-1.0.4.dist-info/WHEEL
blip_sdk-1.0.4.dist-info/top_level.txt
blip_sdk-1.0.4.dist-info/RECORD
